saamfi_sdk/__init__.py
saamfi_sdk/client.py
saamfi_sdk/exceptions.py
saamfi_sdk/models.py
saamfi_sdk/py.typed
saamfi_sdk/services/__init__.py
saamfi_sdk/services/auth.py
saamfi_sdk/services/base.py
saamfi_sdk/services/institutions.py
saamfi_sdk/services/systems.py
saamfi_sdk/services/token.py
saamfi_sdk/services/users.py
saamfi_sdk-0.1.1.dist-info/licenses/LICENSE
saamfi_sdk-0.1.1.dist-info/METADATA
saamfi_sdk-0.1.1.dist-info/WHEEL
saamfi_sdk-0.1.1.dist-info/top_level.txt
saamfi_sdk-0.1.1.dist-info/RECORD
