Metadata-Version: 2.4
Name: saamfi-sdk
Version: 0.1.1
Summary: SDK de Python para conectarse a los servicios SAAMFI - Autenticacion y Autorizacion
Author-email: Universidad ICESI <dev@icesi.edu.co>
License: MIT
Project-URL: Homepage, https://github.com/icesi-dev/saamfi-sdk-python
Project-URL: Documentation, https://saamfi-sdk-python.readthedocs.io
Project-URL: Repository, https://github.com/icesi-dev/saamfi-sdk-python.git
Project-URL: Issues, https://github.com/icesi-dev/saamfi-sdk-python/issues
Keywords: saamfi,authentication,authorization,jwt,security,sdk
Classifier: Development Status :: 3 - Alpha
Classifier: Intended Audience :: Developers
Classifier: License :: OSI Approved :: MIT License
Classifier: Programming Language :: Python :: 3
Classifier: Programming Language :: Python :: 3.8
Classifier: Programming Language :: Python :: 3.9
Classifier: Programming Language :: Python :: 3.10
Classifier: Programming Language :: Python :: 3.11
Classifier: Programming Language :: Python :: 3.12
Classifier: Topic :: Software Development :: Libraries :: Python Modules
Classifier: Topic :: Security
Requires-Python: >=3.8
License-File: LICENSE
Requires-Dist: requests>=2.31.0
Requires-Dist: PyJWT>=2.8.0
Requires-Dist: cryptography>=41.0.0
Requires-Dist: pydantic>=2.5.0
Requires-Dist: python-dotenv>=1.0.0
Provides-Extra: dev
Requires-Dist: pytest>=7.4.0; extra == "dev"
Requires-Dist: pytest-cov>=4.1.0; extra == "dev"
Requires-Dist: pytest-asyncio>=0.21.0; extra == "dev"
Requires-Dist: black>=23.0.0; extra == "dev"
Requires-Dist: flake8>=6.0.0; extra == "dev"
Requires-Dist: mypy>=1.5.0; extra == "dev"
Requires-Dist: isort>=5.12.0; extra == "dev"
Provides-Extra: fastapi
Requires-Dist: fastapi>=0.104.0; extra == "fastapi"
Dynamic: license-file
